{"id":"57d0b6de-d1a2-4e2c-8548-83f54c96b0f3","title":"Postgres","desc":"","updated":1640237319440,"created":1618141186045,"custom":{},"fname":"dev.sql.postgres","type":"note","vault":{"name":"main","fsPath":"main","useFMTitle":false},"contentHash":"525a6edca4688a286712786ed2c9a8a2","links":[],"anchors":{"postgres":{"type":"header","text":"Postgres","value":"postgres","line":8,"column":0,"depth":1},"configuration":{"type":"header","text":"Configuration","value":"configuration","line":10,"column":0,"depth":2},"connection-pooling":{"type":"header","text":"Connection Pooling","value":"connection-pooling","line":15,"column":0,"depth":2},"gotchas":{"type":"header","text":"Gotchas","value":"gotchas","line":20,"column":0,"depth":2},"security":{"type":"header","text":"Security","value":"security","line":29,"column":0,"depth":2},"text-vs-varchar":{"type":"header","text":"Text Vs Varchar","value":"text-vs-varchar","line":33,"column":0,"depth":2},"zfs":{"type":"header","text":"ZFS","value":"zfs","line":37,"column":0,"depth":2}},"children":["9OmPMpSvnD00DNgRLZaiq","J9ugxlvBdatTZHqLd68Vp"],"parent":"ym0pwl1e32z11v6mnou6oka","data":{}}
