{"id":"9OmPMpSvnD00DNgRLZaiq","title":"Backups","desc":"","updated":1643724669700,"created":1643724474576,"custom":{},"fname":"dev.sql.postgres.backups","type":"note","vault":{"name":"main","fsPath":"main","useFMTitle":false},"contentHash":"bcbeb0d6b79b57219c5cb666be0e3afd","links":[],"anchors":{"postgres-backups":{"type":"header","text":"Postgres Backups","value":"postgres-backups","line":8,"column":0,"depth":1},"pgdumpall":{"type":"header","text":"Pgdumpall","value":"pgdumpall","line":10,"column":0,"depth":2}},"children":[],"parent":"57d0b6de-d1a2-4e2c-8548-83f54c96b0f3","data":{}}
