{"id":"d650289d-5586-446b-80fa-a4f3f8c22f4f","title":"Systems and Gestalt Theory","desc":"A comparison of systems and gestalt theory","updated":1622273289681,"created":1622266828608,"custom":{},"fname":"humans.systems.systems-and-gestalt-theory","type":"note","vault":{"fsPath":"human-dynamics","name":"Human Dynamics","useFMTitle":false},"contentHash":"1f4f8abd00ba90d26b5342a6ab291e9d","links":[{"type":"wiki","from":{"fname":"humans.systems.systems-and-gestalt-theory","id":"d650289d-5586-446b-80fa-a4f3f8c22f4f","vaultName":"Human Dynamics"},"value":"humans.paradoxical-theory-of-change","alias":"change should come from the individual","position":{"start":{"line":22,"column":36,"offset":559},"end":{"line":22,"column":114,"offset":637},"indent":[]},"xvault":false,"sameFile":false,"to":{"fname":"humans.paradoxical-theory-of-change"}},{"from":{"id":"0549edd2-8f12-4710-8d1c-2b7e610ac600","fname":"humans.systems.intervention","vaultName":"Human Dynamics"},"type":"backlink","position":{"start":{"line":6,"column":4,"offset":142},"end":{"line":6,"column":49,"offset":187},"indent":[]},"value":"humans.systems.systems-and-gestalt-theory"}],"anchors":{"systems-and-gestalt-theory":{"type":"header","text":"Systems And Gestalt Theory","value":"systems-and-gestalt-theory","line":8,"column":0,"depth":1},"systems-theory":{"type":"header","text":"Systems Theory","value":"systems-theory","line":10,"column":0,"depth":2},"gestalt-theory":{"type":"header","text":"Gestalt Theory","value":"gestalt-theory","line":18,"column":0,"depth":2}},"children":[],"parent":"b581d909-3f25-4508-a61d-ce64a04c9a3b","data":{}}
